odoo10_addon_account_cutoff_prepaid-10.0.1.1.0-py2.7-nspkg.pth
odoo/addons/account_cutoff_prepaid/README.rst
odoo/addons/account_cutoff_prepaid/__init__.py
odoo/addons/account_cutoff_prepaid/__manifest__.py
odoo/addons/account_cutoff_prepaid/i18n/am.po
odoo/addons/account_cutoff_prepaid/i18n/ar.po
odoo/addons/account_cutoff_prepaid/i18n/de.po
odoo/addons/account_cutoff_prepaid/i18n/el_GR.po
odoo/addons/account_cutoff_prepaid/i18n/es.po
odoo/addons/account_cutoff_prepaid/i18n/es_ES.po
odoo/addons/account_cutoff_prepaid/i18n/es_MX.po
odoo/addons/account_cutoff_prepaid/i18n/fi.po
odoo/addons/account_cutoff_prepaid/i18n/fr.po
odoo/addons/account_cutoff_prepaid/i18n/fr_FR.po
odoo/addons/account_cutoff_prepaid/i18n/hr.po
odoo/addons/account_cutoff_prepaid/i18n/hr_HR.po
odoo/addons/account_cutoff_prepaid/i18n/it.po
odoo/addons/account_cutoff_prepaid/i18n/nb.po
odoo/addons/account_cutoff_prepaid/i18n/nb_NO.po
odoo/addons/account_cutoff_prepaid/i18n/nl.po
odoo/addons/account_cutoff_prepaid/i18n/nl_BE.po
odoo/addons/account_cutoff_prepaid/i18n/nl_NL.po
odoo/addons/account_cutoff_prepaid/i18n/pt.po
odoo/addons/account_cutoff_prepaid/i18n/pt_BR.po
odoo/addons/account_cutoff_prepaid/i18n/ro.po
odoo/addons/account_cutoff_prepaid/i18n/sk.po
odoo/addons/account_cutoff_prepaid/i18n/sl.po
odoo/addons/account_cutoff_prepaid/i18n/tr.po
odoo/addons/account_cutoff_prepaid/i18n/zh_CN.po
odoo/addons/account_cutoff_prepaid/images/prepaid_revenue_done.jpg
odoo/addons/account_cutoff_prepaid/images/prepaid_revenue_draft.jpg
odoo/addons/account_cutoff_prepaid/images/prepaid_revenue_journal_entry.jpg
odoo/addons/account_cutoff_prepaid/migrations/7.0.0.2/pre-migration.py
odoo/addons/account_cutoff_prepaid/models/__init__.py
odoo/addons/account_cutoff_prepaid/models/account_config_settings.py
odoo/addons/account_cutoff_prepaid/models/account_cutoff.py
odoo/addons/account_cutoff_prepaid/models/company.py
odoo10_addon_account_cutoff_prepaid-10.0.1.1.0.dist-info/DESCRIPTION.rst
odoo10_addon_account_cutoff_prepaid-10.0.1.1.0.dist-info/METADATA
odoo10_addon_account_cutoff_prepaid-10.0.1.1.0.dist-info/RECORD
odoo10_addon_account_cutoff_prepaid-10.0.1.1.0.dist-info/WHEEL
odoo10_addon_account_cutoff_prepaid-10.0.1.1.0.dist-info/metadata.json
odoo10_addon_account_cutoff_prepaid-10.0.1.1.0.dist-info/namespace_packages.txt
odoo10_addon_account_cutoff_prepaid-10.0.1.1.0.dist-info/top_level.txt
